wrap_engine/__init__.py
wrap_engine/app.py
wrap_engine/condition_checker.py
wrap_engine/environ_data.py
wrap_engine/event.py
wrap_engine/event_generator.py
wrap_engine/event_id_pool.py
wrap_engine/exception.py
wrap_engine/id_generator.py
wrap_engine/image_generator.py
wrap_engine/image_modifier.py
wrap_engine/image_utils.py
wrap_engine/math_utils.py
wrap_engine/message_broker.py
wrap_engine/object_manager.py
wrap_engine/pygame_utils.py
wrap_engine/sprite.py
wrap_engine/sprite_of_type.py
wrap_engine/sprite_text.py
wrap_engine/sprite_type.py
wrap_engine/sprite_type_costume.py
wrap_engine/sprite_type_costume_holder.py
wrap_engine/sprite_type_factory.py
wrap_engine/sprite_type_loader.py
wrap_engine/timer.py
wrap_engine/transl.py
wrap_engine/world.py
wrap_engine-0.2.3.2.21220701.dist-info/METADATA
wrap_engine-0.2.3.2.21220701.dist-info/WHEEL
wrap_engine-0.2.3.2.21220701.dist-info/top_level.txt
wrap_engine-0.2.3.2.21220701.dist-info/RECORD
