Metadata-Version: 2.1
Name: wrap-engine
Version: 0.2.3.2.21220701
Requires-Dist: pygame (==2.0.1)
